pyshuii/__init__.py
pyshuii/chain_mapping.py
pyshuii/clients/CosmWasmClient.py
pyshuii/clients/EthereumClient.py
pyshuii/clients/ProxyClient.py
pyshuii/clients/__init__.py
pyshuii/indexers/MultiDocument.py
pyshuii/indexers/SingleDocument.py
pyshuii/indexers/__init__.py
pyshuii/retrieve.py
pyshuii/retrievers/Main.py
pyshuii/retrievers/__init__.py
pyshuii/retrievers/cw721.py
pyshuii/retrievers/erc721.py
pyshuii/utils/__init__.py
pyshuii/utils/traceCast.py
pyshuii-0.1.0.dist-info/LICENSE
pyshuii-0.1.0.dist-info/WHEEL
pyshuii-0.1.0.dist-info/METADATA
pyshuii-0.1.0.dist-info/RECORD
