Metadata-Version: 2.1
Name: pyshuii
Version: 0.1.0
Summary: 
License: MIT
Author: prathik
Author-email: 37804760+prmali@users.noreply.github.com
Requires-Python: >=3.9,<4.0
Classifier: License :: OSI Approved :: MIT License
Classifier: Programming Language :: Python :: 3
Classifier: Programming Language :: Python :: 3.9
Classifier: Programming Language :: Python :: 3.10
Classifier: Programming Language :: Python :: 3.11
Requires-Dist: aiohttp (==3.8.1)
Requires-Dist: asyncio (==3.4.3)
Requires-Dist: cosmpy (==0.5.1)
Requires-Dist: tqdm (==4.64.0)
Requires-Dist: web3 (==5.30.0)
